wild_requests/__init__.py
wild_requests/async_generator.py
wild_requests/dict_return.py
wild_requests-0.0.5.dist-info/LICENSE
wild_requests-0.0.5.dist-info/METADATA
wild_requests-0.0.5.dist-info/WHEEL
wild_requests-0.0.5.dist-info/top_level.txt
wild_requests-0.0.5.dist-info/RECORD
