Metadata-Version: 2.1
Name: wild-requests
Version: 0.0.5
Summary: Just a module that provides some tools for downloading.
Home-page: https://github.com/taux1c/wild_requests
Author: Taux1c
License-File: LICENSE
Requires-Dist: httpx ~=0.25.0
